{
  "unid": "SITE4FC5KK2I",
  "title": "Недвижимость, РњРёРЅСЃРє, РџРѕР»С‚Р°РІСЃРєР°СЏ СѓР»., 10",
  "price": "договорная",
  "currency": "USD",
  "type": "Квартира",
  "rooms": "",
  "area": "Не указана",
  "location": null,
  "description": "Р’Р°С€РµРјСѓ РІРЅРёРјР°РЅРёСЋ РїСЂРµРґР»Р°РіР°РµС‚СЃСЏ Рє РїСЂРёРѕР±СЂРµС‚РµРЅРёСЋ Р°РґРјРёРЅРёСЃС‚СЂР°С‚РёРІРЅРѕ-С…РѕР·СЏР№СЃС‚РІРµРЅРЅРѕРµ РґРІСѓС…СЌС‚Р°Р¶РЅРѕРµ РєРёСЂРїРёС‡РЅРѕРµ Р·РґР°РЅРёРµ РѕР±С‰РµР№ РїР»РѕС‰Р°РґСЊСЋ 778.4 РєРІ.Рј (574,2 РєРІ.Рј РЅРѕСЂРјРёСЂСѓРµРјР°СЏ) РїРѕ СѓР»РёС†Рµ РџРѕР»С‚Р°РІСЃРєРѕР№ РЅР° Р±Р»Р°РіРѕСѓСЃС‚СЂРѕРµРЅРЅРѕРј Р·РµРјРµР»СЊРЅРѕРј СѓС‡Р°СЃС‚РєРµ РЅР° 8,04 СЃРѕС‚РєРё СЃ РїСЂР°РІРѕРј Р°СЂРµРЅРґС‹ Рё СЃРѕР±СЃС‚РІРµРЅРЅРѕР№ РїР°СЂРєРѕРІРєРѕР№. РќРѕРІР°СЏ СЃРѕРІСЂРµРјРµРЅРЅР°СЏ РѕС‚РґРµР»РєР° РІ С…РѕР»Р»Рµ, РєРѕСЂРёРґРѕСЂР°С…, РѕС„РёСЃР°С…. РћС…СЂР°РЅР°, Р°РґРјРёРЅРёСЃС‚СЂР°С‚РѕСЂ, РІРёРґРµРѕРЅР°Р±Р»СЋРґРµРЅРёРµ, СЂР°Р·РґРµР»СЊРЅС‹Рµ СЃР°РЅСѓР·Р»С‹ (РјСѓР¶СЃРєРѕР№ Рё Р¶РµРЅСЃРєРёР№), РєРѕСЂРёРґРѕСЂРЅР°СЏ СЃРёСЃС‚РµРјР°, РµСЃС‚РµСЃС‚РІРµРЅРЅРѕРµ РѕСЃРІРµС‰РµРЅРёРµ, РЅРµРґР°Р»РµРєРѕ РѕСЃС‚Р°РЅРѕРІРєРё РѕР±С‰РµСЃС‚РІРµРЅРЅРѕРіРѕ С‚СЂР°РЅСЃРїРѕСЂС‚Р° &ndash; РљР°РјРІРѕР»СЊРЅС‹Р№ РєРѕРјР±РёРЅР°С‚ Рё РґСЂСѓРіРёРµ. РќР°Р»РёС‡РёРµ Р°СЂРµРЅРґР°С‚РѕСЂРѕРІ, С‡С‚Рѕ РїСЂРµРґРїРѕР»Р°РіР°РµС‚ СЃС‚Р°Р±РёР»СЊРЅС‹Р№ РґРѕС…РѕРґ РєР°Рє РІР»РѕР¶РµРЅРёРµ. Р—РґР°РЅРёРµ РёРјРµРµС‚ СЃР»РµРґСѓСЋС‰РёРµ С…Р°СЂР°РєС‚РµСЂРёСЃС‚РёРєРё: РЅР°РёРјРµРЅРѕРІР°РЅРёРµ - РђРґРјРёРЅРёСЃС‚СЂР°С‚РёРІРЅРѕРµ Р·РґР°РЅРёРµ, РЅР°Р·РЅР°С‡РµРЅРёРµ - Р—РґР°РЅРёРµ Р°РґРјРёРЅРёСЃС‚СЂР°С‚РёРІРЅРѕ-С…РѕР·СЏР№СЃС‚РІРµРЅРЅРѕРµ, РіРѕРґ РїРѕСЃС‚СЂРѕР№РєРё - 1952, РіРѕРґ СЂРµРєРѕРЅСЃС‚СЂСѓРєС†РёРё - 2020; РѕР±С‰Р°СЏ РїР»РѕС‰Р°РґСЊ Р·РґР°РЅРёСЏ - 788,5 Рј2; РЅРѕСЂРјРёСЂСѓРµРјР°СЏ РїР»РѕС‰Р°РґСЊ Р·РґР°РЅРёСЏ - 574,2Рј2; СЌС‚Р°Р¶РЅРѕСЃС‚СЊ Р·РґР°РЅРёСЏ - 2; РєРѕР»РёС‡РµСЃС‚РІРѕ РїРѕРјРµС‰РµРЅРёР№ - 50; РєРѕР»РёС‡РµСЃС‚РІРѕ РєР°Р±РёРЅРµС‚РѕРІ - 30; 3 СЃР°РЅСѓР·Р»Р°, РєРѕСЂРёРґРѕСЂС‹, РІРµСЃС‚РёР±СЋР»Рё, Р»РµСЃС‚РЅРёС‡РЅС‹Р№ РјР°СЂС€; С„СѓРЅРґР°РјРµРЅС‚ - Р±СѓС‚РѕР±РµС‚РѕРЅ; РјР°С‚РµСЂРёР°Р» СЃС‚РµРЅ - РєРёСЂРїРёС‡; РїРµСЂРµРєСЂС‹С‚РёСЏ - РґРµСЂРµРІРѕ; РєРѕРЅСЃС‚СЂСѓРєС†РёСЏ Р·РґР°РЅРёСЏ - Р±РµСЃРєР°СЂРєР°СЃРЅР°СЏ, РєСЂС‹С€Р° - РјРµС‚Р°Р»Р»РѕС‡РµСЂРµРїРёС†Р°; РїРѕР»С‹ - РїР»РёС‚РєР°, РґРѕСЃРєР°, Р±РµС‚РѕРЅ, РїР°СЂРєРµС‚, Р»РёРЅРѕР»РµСѓРј, РѕРєРЅР° - РџР’РҐ; С‚РµР»РµС„РѕРЅРёР·Р°С†РёСЏ - РµСЃС‚СЊ; СЌР»РµРєС‚СЂРѕСЃРЅР°Р±Р¶РµРЅРёРµ - С†РµРЅС‚СЂР°Р»СЊРЅРѕРµ; РІРѕРґРѕРїСЂРѕРІРѕРґ - С†РµРЅС‚СЂР°Р»СЊРЅС‹Р№, РєР°РЅР°Р»РёР·Р°С†РёСЏ - С†РµРЅС‚СЂР°Р»СЊРЅРѕРµ; РѕС‚РѕРїР»РµРЅРёРµ - С†РµРЅС‚СЂР°Р»СЊРЅРѕРµ; СЂР°Р·РјРµСЂ Р·РµРјРµР»СЊРЅРѕРіРѕ СѓС‡Р°СЃС‚РєР° - 0,0804 РіР°, РЅР°Р·РЅР°С‡РµРЅРёРµ СѓС‡Р°СЃС‚РєР° - РґР»СЏ СЌРєСЃРїР»СѓР°С‚Р°С†РёРё Рё РѕР±СЃР»СѓР¶РёРІР°РЅРёСЏ Р°РґРјРёРЅРёСЃС‚СЂР°С‚РёРІРЅРѕРіРѕ Р·РґР°РЅРёСЏ. Р›РёС†РµРЅР·РёСЏ: 02240/446 РњР® Р Р‘, 11.07.2022",
  "images": [
    "https://files.realt.by/img/62/fea2ab44-ad97-11f0-aafa-0242ac120002.jpg",
    "https://files.realt.by/img/62/fe8ec2a0-ad97-11f0-81bc-0242ac120002.jpg",
    "https://files.realt.by/img/62/fe8c9818-ad97-11f0-8c1d-0242ac120002.jpg",
    "https://files.realt.by/img/62/fe983010-ad97-11f0-b36f-0242ac120002.jpg",
    "https://files.realt.by/img/62/fe985342-ad97-11f0-a405-0242ac120002.jpg",
    "https://files.realt.by/img/62/fe8637d4-ad97-11f0-951a-0242ac120002.jpg",
    "https://files.realt.by/img/62/fe53b3a4-ad97-11f0-8b55-0242ac120002.jpg",
    "https://files.realt.by/img/62/fe4a45b2-ad97-11f0-b640-0242ac120002.jpg",
    "https://files.realt.by/img/62/fe537b82-ad97-11f0-99a8-0242ac120002.jpg",
    "https://files.realt.by/img/62/fe55400c-ad97-11f0-8d53-0242ac120002.jpg",
    "https://files.realt.by/img/62/fe6429be-ad97-11f0-8f63-0242ac120002.jpg",
    "https://files.realt.by/img/62/fe892098-ad97-11f0-b5c4-0242ac120002.jpg",
    "https://files.realt.by/img/62/fe4de154-ad97-11f0-ab8b-0242ac120002.jpg",
    "https://files.realt.by/img/62/fe4e3cf8-ad97-11f0-b3c8-0242ac120002.jpg",
    "https://files.realt.by/img/62/fe61a964-ad97-11f0-8e28-0242ac120002.jpg",
    "https://files.realt.by/img/62/fe5e5bba-ad97-11f0-9ee6-0242ac120002.jpg",
    "https://files.realt.by/img/62/fe67ad82-ad97-11f0-b665-0242ac120002.jpg",
    "https://files.realt.by/img/62/fe862c3a-ad97-11f0-b916-0242ac120002.jpg",
    "https://files.realt.by/img/62/fe8392cc-ad97-11f0-bc75-0242ac120002.jpg",
    "https://files.realt.by/img/62/fe80c1fa-ad97-11f0-a212-0242ac120002.jpg",
    "https://files.realt.by/img/62/fe726196-ad97-11f0-8e94-0242ac120002.jpg",
    "https://files.realt.by/img/62/fe6fcad0-ad97-11f0-a762-0242ac120002.jpg"
  ]
}