{
  "unid": "SITEZAA0YSZ5",
  "title": "Недвижимость, РњРёРЅСЃРє, РђРІС‚РѕР·Р°РІРѕРґСЃРєРѕР№ РїРµСЂ., 8",
  "price": 50100,
  "currency": "USD",
  "type": "Квартира",
  "rooms": "3",
  "area": "46.3 / 37.1 / 6.9 м²",
  "location": null,
  "description": "РџСЂРѕРґР°РµС‚СЃСЏ РїСЂРѕСЃС‚РѕСЂРЅР°СЏ С‚СЂРµС…РєРѕРјРЅР°С‚РЅР°СЏ РєРІР°СЂС‚РёСЂР° РІ РєРёСЂРїРёС‡РЅРѕРј Р±Р»РѕРєРёСЂРѕРІР°РЅРЅРѕРј РґРѕРјРµ СЃ РѕС‚РґРµР»СЊРЅС‹Рј РІС…РѕРґРѕРј. РџРѕС‡РµРјСѓ СЃС‚РѕРёС‚ РєСѓРїРёС‚СЊ СЌС‚Сѓ РєРІР°СЂС‚РёСЂСѓ - Р’С‹РіРѕРґРЅРѕРµ СЂР°СЃРїРѕР»РѕР¶РµРЅРёРµ &ndash; РІСЃРµРіРѕ 10&ndash;12 РјРёРЅСѓС‚ РїРµС€РєРѕРј РґРѕ СЃС‚Р°РЅС†РёРё РјРµС‚СЂРѕ РђРІС‚РѕР·Р°РІРѕРґСЃРєР°СЏ, СЂСЏРґРѕРј РЅРѕРІР°СЏ РІС‹СЃРѕС‚РЅР°СЏ Р·Р°СЃС‚СЂРѕР№РєР° СЃ СЂР°Р·РІРёС‚РѕР№ РёРЅС„СЂР°СЃС‚СЂСѓРєС‚СѓСЂРѕР№. - РўРёС…РёР№ СЂР°Р№РѕРЅ &ndash; СЃРїРѕРєРѕР№РЅС‹Рµ СЃРѕСЃРµРґРё, РѕС‚СЃСѓС‚СЃС‚РІРёРµ Р°СЃРѕС†РёР°Р»СЊРЅС‹С… СЌР»РµРјРµРЅС‚РѕРІ. - Р’СЃРµ РЅРµРѕР±С…РѕРґРёРјРѕРµ СЂСЏРґРѕРј &ndash; РјР°РіР°Р·РёРЅС‹, РІРєР»СЋС‡Р°СЏ Р•РІСЂРѕРѕРїС‚, СЃСЂРµРґРЅСЏСЏ С€РєРѕР»Р°, РіРёРјРЅР°Р·РёСЏ, РґРµС‚СЃРєРёР№ СЃР°Рґ РІ С€Р°РіРѕРІРѕР№ РґРѕСЃС‚СѓРїРЅРѕСЃС‚Рё. - РљРѕРјС„РѕСЂС‚РЅС‹Рµ СѓСЃР»РѕРІРёСЏ &ndash; С†РµРЅС‚СЂР°Р»СЊРЅРѕРµ РѕС‚РѕРїР»РµРЅРёРµ Рё РІРѕРґРѕСЃРЅР°Р±Р¶РµРЅРёРµ, РІС‹СЃРѕРєРёРµ РїРѕС‚РѕР»РєРё 2,70 Рј, РѕС‚РґРµР»СЊРЅС‹Р№ РІС…РѕРґ. - РџСЂРѕСЃС‚РѕСЂРЅР°СЏ РїР»Р°РЅРёСЂРѕРІРєР° &ndash; РѕР±С‰Р°СЏ РїР»РѕС‰Р°РґСЊ РїРѕ РЎРќР‘ 46,3 Рј2, РєСѓС…РЅСЏ 6,9 Рј2, С‡С‚Рѕ СѓРґРѕР±РЅРѕ РґР»СЏ СЃРµРјСЊРё. - РџРµСЂСЃРїРµРєС‚РёРІР° &ndash; СЂР°Р№РѕРЅ СЃ РЅРѕРІРѕР№ Р·Р°СЃС‚СЂРѕР№РєРѕР№, С‡С‚Рѕ РјРѕР¶РµС‚ РїРѕРІС‹СЃРёС‚СЊ Р»РёРєРІРёРґРЅРѕСЃС‚СЊ РЅРµРґРІРёР¶РёРјРѕСЃС‚Рё РІ Р±СѓРґСѓС‰РµРј. Р§РёСЃС‚Р°СЏ РїСЂРѕРґР°Р¶Р°, Р±РµР· РѕР±СЂРµРјРµРЅРµРЅРёР№ РћС‚Р»РёС‡РЅС‹Р№ РІР°СЂРёР°РЅС‚ РґР»СЏ Р¶РёР·РЅРё РёР»Рё РёРЅРІРµСЃС‚РёС†РёР№. Р—РІРѕРЅРёС‚Рµ, С‡С‚РѕР±С‹ СѓР·РЅР°С‚СЊ РїРѕРґСЂРѕР±РЅРѕСЃС‚Рё Рё РґРѕРіРѕРІРѕСЂРёС‚СЊСЃСЏ Рѕ РїСЂРѕСЃРјРѕС‚СЂРµ. Р›РёС†РµРЅР·РёСЏ: 02240/446 РѕС‚ 11.07.2022, РњРёРЅРёСЃС‚РµСЂСЃС‚РІРѕ СЋСЃС‚РёС†РёРё Р Р‘",
  "images": [
    "https://files.realt.by/img/62/4259e7e2-5f11-11f0-b667-0242ac120003.jpg"
  ]
}